{"type":"result","timestamp":"2023-06-22T22:41:04Z","ping":{"jitter":0.098,"latency":0.950,"low":0.896,"high":1.100},"download":{"bandwidth":66621053,"bytes":673118712,"elapsed":9825,"latency":{"iqm":1.939,"low":0.967,"high":17.425,"jitter":1.598}},"upload":{"bandwidth":67720282,"bytes":820347320,"elapsed":12120,"latency":{"iqm":1.314,"low":0.943,"high":19.972,"jitter":0.988}},"packetLoss":0,"isp":"Altagen JSC","interface":{"internalIp":"192.168.0.2","name":"","macAddr":"18:C0:4D:0A:E6:CF","isVpn":false,"externalIp":"46.151.156.118"},"server":{"id":48192,"host":"speedtest.aeza.network","port":8080,"name":"Aeza.net","location":"Moscow","country":"Russia","ip":"194.26.229.25"},"result":{"id":"231cd7e8-1ecf-4394-84c5-4acf609b37d5","url":"https://www.speedtest.net/result/c/231cd7e8-1ecf-4394-84c5-4acf609b37d5","persisted":true}}
